batchgit/__init__.py
batchgit/cli.py
bgit/__init__.py
bgit/cli.py
batchgit-0.0.2.dist-info/METADATA
batchgit-0.0.2.dist-info/WHEEL
batchgit-0.0.2.dist-info/entry_points.txt
batchgit-0.0.2.dist-info/top_level.txt
batchgit-0.0.2.dist-info/RECORD
