Metadata-Version: 2.1
Name: batchgit
Version: 0.0.2
Summary: Tool to manage multiple git repos
Home-page: UNKNOWN
Author: Hong Jiang
Author-email: lazyseq@gmail.com
License: UNKNOWN
Platform: UNKNOWN
Requires-Dist: gitpython
Requires-Dist: pyyaml
